{
  "id": "s1_1_data_collection_game",
  "type": "transition",
  "beats": [
    {
      "type": "scene",
      "method": "add",
      "tangible_id": "data_collection_game_blocks",
      "tangible_type": "data_collection_game",
      "params": {
        "description": "Minis characters appear in animated counting scenario. Four piles of colored blocks visible: Red, Blue, Green, Yellow.",
        "categories": [
          "Red blocks",
          "Blue blocks",
          "Green blocks",
          "Yellow blocks"
        ],
        "valid_values": [
          10,
          15,
          20,
          25,
          30,
          35,
          40,
          45
        ]
      },
      "flag": "placeholder — data_collection_game toy spec not yet defined; params structure is best-guess based on game_specifications field"
    },
    {
      "type": "dialogue",
      "text": "The Minis are organizing their collections! Let's help them count."
    },
    {
      "type": "current_scene",
      "elements": [
        {
          "tangible_id": "data_collection_game_blocks",
          "description": "Minis characters with four piles of colored blocks: Red, Blue, Green, Yellow. Counting interaction active.",
          "tangible_type": "data_collection_game",
          "categories": [
            "Red blocks",
            "Blue blocks",
            "Green blocks",
            "Yellow blocks"
          ]
        }
      ],
      "flag": "placeholder — data_collection_game toy spec not yet defined; current_scene structure reflects anticipated state"
    }
  ],
  "_generated_at": "2026-05-05T20:06:08.434979+00:00"
}
