{"lessons":
[
  {
  "purpose": "Main teaching of equal parts and fraction concept",
  "core_fractions": ["1/2", "1/3", "1/4", "1/6", "1/8"],
  "vocabulary_introduced": ["equal parts", "whole", "partition"],
  "cra_sequence": "Concrete → Relational → Abstract",
  "interactions": [
    {
      "id": 1,
      "title": "Introduction to Grids & Equal Parts",
      "interaction_type": "identify",
      "cognitive_demand": "recall",
      "task": "Count squares in grids",
      "fractions_involved": ["1/4", "1/3"],
      "vocabulary_staging": ["equal parts"],
      "misconceptions_addressed": ["#2"]
    },
    {
      "id": 2,
      "title": "Eight Equal Parts & Whole",
      "interaction_type": "identify",
      "cognitive_demand": "recall",
      "task": "Count parts in larger grid",
      "fractions_involved": ["1/8"],
      "vocabulary_staging": ["whole"],
      "misconceptions_addressed": ["#2"]
    },
    {
      "id": 3,
      "title": "Creating Thirds & Partition",
      "interaction_type": "create",
      "cognitive_demand": "apply",
      "task": "Partition rectangle into thirds",
      "fractions_involved": ["1/3"],
      "vocabulary_staging": ["partition"],
      "misconceptions_addressed": ["#1"]
    },
    {
      "id": 4,
      "title": "Partitioning into Fourths",
      "interaction_type": "create",
      "cognitive_demand": "apply",
      "task": "Partition square into fourths",
      "fractions_involved": ["1/4"],
      "vocabulary_staging": [],
      "misconceptions_addressed": ["#1"]
    },
    {
      "id": 5,
      "title": "Partitioning Circles",
      "interaction_type": "create",
      "cognitive_demand": "apply",
      "task": "Partition circles into halves and fourths",
      "fractions_involved": ["1/2", "1/4"],
      "vocabulary_staging": [],
      "misconceptions_addressed": ["#2"]
    },
    {
      "id": 6,
      "title": "Same Equal Parts Different Representations",
      "interaction_type": "compare",
      "cognitive_demand": "analyze",
      "task": "Identify shapes with same number of equal parts",
      "fractions_involved": ["1/6"],
      "vocabulary_staging": [],
      "misconceptions_addressed": ["#2"]
    }
  ]
}]}
