[
  {
    "id": "s1_1_opening_frame",
    "dialogues": [
      {
        "text": "You've been describing arrays and building expressions and equations. Let's connect what you discovered.",
        "context": "lesson"
      }
    ]
  },
  {
    "id": "s1_2_real_world_array_to_dot",
    "dialogues": [
      {
        "text": "Look at these two pictures. A muffin tin and a dot array. What expression describes them both by rows?",
        "context": "lesson"
      },
      {
        "text": "2 times 4. Whether it's muffins or dots, 2 rows of 4 is 2 times 4. The arrangement is what matters, not what's in the spots.",
        "context": "on_correct"
      }
    ]
  },
  {
    "id": "s2_1_same_array_two_products",
    "dialogues": [
      {
        "text": "Here's an array you've worked with. Described by rows, it's 3 times 5 equals 15. Described by columns, it's 5 times 3 equals 15. Look at both equations. What do you notice about the products?",
        "context": "lesson"
      },
      {
        "text": "You noticed it's the same array, two descriptions, same product. Interesting, right? We'll dig into that next time.",
        "context": "on_correct"
      }
    ]
  },
  {
    "id": "s3_1_arrays_real_world",
    "dialogues": [
      {
        "text": "Arrays are not just in math. Look at these four pictures. Which ones are arrays?",
        "context": "lesson"
      },
      {
        "text": "Egg carton, parking lot, window pane. Arrays are everywhere. Same rows and columns structure you have been working with.",
        "context": "on_correct"
      },
      {
        "text": "Once you see arrays, you notice them everywhere. Same math, rows times columns, whether it is eggs, cars, or windows.",
        "context": "lesson"
      }
    ]
  },
  {
    "id": "s3_2_metacognitive_reflection",
    "dialogues": [
      {
        "text": "If you remember one thing from today, what would it be?",
        "context": "lesson"
      },
      {
        "text": "Rows and columns. That's what makes an array different from just a bunch of groups. You'll keep using that.",
        "context": "on_correct"
      },
      {
        "text": "That's the rule. What you SAY determines what you WRITE. Precise language, precise math.",
        "context": "on_correct"
      },
      {
        "text": "Two descriptions, two expressions, one array. That's something we'll come back to next time.",
        "context": "on_correct"
      }
    ]
  },
  {
    "id": "s3_3_identity_building_closure",
    "dialogues": [
      {
        "text": "You came in knowing equal groups in bags and boxes. Now you see them lined up as arrays with rows and columns. You describe arrays two ways. You write the expression for each description. And you find the product.",
        "context": "lesson"
      },
      {
        "text": "You noticed something in those two products. Next time, we'll figure out WHY that happens and whether it's always true.",
        "context": "lesson"
      },
      {
        "text": "Get ready.",
        "context": "lesson"
      }
    ]
  }
]