{
  "id": "s2_8_section_transition",
  "type": "transition",
  "beats": [
    {
      "type": "scene",
      "method": "add",
      "tangible_id": "data_table",
      "tangible_type": "data_table",
      "params": {
        "description": "Data table appears showing numeric values only."
      }
    },
    {
      "type": "dialogue",
      "text": "So far, some parts of the graphs were already filled in for you. Now let's see if you can build a whole graph on your own."
    },
    {
      "type": "current_scene",
      "elements": [
        {
          "tangible_id": "data_table",
          "description": "Data table showing numeric values only.",
          "tangible_type": "data_table"
        }
      ]
    }
  ],
  "_generated_at": "2026-04-20T17:02:04.030327+00:00"
}