[
  {
    "id": "s1_1_transition_exit_check",
    "type": "transition",
    "beats": [
      {
        "type": "dialogue",
        "text": "You proved that when you change the order of the factors, the product stays the same. You used highlighting, rotation, and turn-around facts. Let's see what you know.",
        "id": "s1_1_transition_exit_check_b0",
        "_notion_block_id": "33e5917e-ac52-8108-b569-e975bc7dfdcf"
      },
      {
        "type": "current_scene",
        "elements": [],
        "id": "s1_1_transition_exit_check_b1"
      }
    ],
    "_generated_at": "2026-04-10T21:22:21.758116+00:00",
    "_notion_block_id": "33e5917e-ac52-810b-9b80-e6fa34684462"
  },
  {
    "id": "s1_2_dual_expression_building",
    "beats": [
      {
        "type": "scene",
        "method": "add",
        "tangible_id": "arrays_6x7",
        "tangible_type": "arrays",
        "params": {
          "mode": "reading",
          "display_mode": "dots",
          "rows": 6,
          "columns": 7,
          "emphasis": "rows",
          "description": "6×7 dot array appears with row emphasis — 6 horizontal bands highlighted."
        },
        "id": "s1_2_dual_expression_building_b0",
        "_notion_block_id": "33e5917e-ac52-8158-9589-d8bf9b18e7f3"
      },
      {
        "type": "scene",
        "method": "add",
        "tangible_id": "equation_builder_rows",
        "tangible_type": "equation_builder",
        "params": {
          "template": [
            "__",
            "×",
            "__",
            "=",
            "__"
          ],
          "style": "equation",
          "tiles": [
            5,
            6,
            7,
            8,
            40,
            42,
            46,
            48
          ],
          "description": "Equation builder appears in equation mode: three blank slots with multiplication and equals signs. Tiles available: 5, 6, 7, 8, 40, 42, 46, 48."
        },
        "id": "s1_2_dual_expression_building_b1",
        "_notion_block_id": "33e5917e-ac52-8176-bd8b-fe95259ef4fd"
      },
      {
        "type": "dialogue",
        "text": "Here's an array with the rows highlighted. Build the equation for the rows.",
        "id": "s1_2_dual_expression_building_b2",
        "_notion_block_id": "33e5917e-ac52-811f-88ba-cbd1e2ceffe0"
      },
      {
        "type": "prompt",
        "text": "Build the equation for the rows.",
        "tool": "place_tile",
        "target": "equation_builder_rows",
        "validator": [
          {
            "condition_id": "correct",
            "condition": {
              "placed": {
                "groups": 6,
                "items": 7,
                "total": 42
              }
            },
            "description": "Student placed 6 × 7 = 42, correct",
            "is_correct": true,
            "beats": [
              {
                "type": "dialogue",
                "text": "Right. 6 rows of 7. 6 times 7 equals 42.",
                "id": "s1_2_dual_expression_building_b3_v0_b0"
              }
            ]
          },
          {
            "condition": {
              "incorrect_count": 1
            },
            "description": "Student placed incorrect tiles on first attempt for row equation",
            "is_correct": false,
            "beats": [
              {
                "type": "dialogue",
                "text": "Not quite. Count the rows — the horizontal bands.",
                "id": "s1_2_dual_expression_building_b3_v1_b0"
              }
            ]
          },
          {
            "condition": {
              "incorrect_count": 2
            },
            "description": "Student placed incorrect tiles on second attempt for row equation",
            "is_correct": false,
            "beats": [
              {
                "type": "scene",
                "method": "update",
                "tangible_id": "arrays_6x7",
                "params": {
                  "description": "One row pulses to show what counts as a row."
                },
                "id": "s1_2_dual_expression_building_b3_v2_b0"
              },
              {
                "type": "dialogue",
                "text": "Let's think about this together. The rows are highlighted. There are 6 rows. Each row has 7 dots.",
                "id": "s1_2_dual_expression_building_b3_v2_b1"
              }
            ]
          },
          {
            "condition": {},
            "description": "Student placed incorrect tiles three or more times. System models the answer.",
            "is_correct": false,
            "beats": [
              {
                "type": "scene",
                "method": "animate",
                "tangible_id": "equation_builder_rows",
                "params": {
                  "event": "place_tiles",
                  "status": "confirmed",
                  "description": "System places tiles 6, 7, and 42 into slots.",
                  "tiles": [
                    6,
                    7,
                    42
                  ]
                },
                "id": "s1_2_dual_expression_building_b3_v3_b0"
              },
              {
                "type": "dialogue",
                "text": "Let me show you how this works. I count the rows: 6. I count the dots in one row: 7. So the equation is 6 times 7 equals 42.",
                "id": "s1_2_dual_expression_building_b3_v3_b1"
              }
            ]
          }
        ],
        "id": "s1_2_dual_expression_building_b3",
        "_notion_block_id": "33e5917e-ac52-811d-b1be-cac60719f66c"
      },
      {
        "type": "current_scene",
        "elements": [
          {
            "tangible_id": "arrays_6x7",
            "description": "6×7 dot array with row emphasis — 6 horizontal bands highlighted.",
            "tangible_type": "arrays",
            "mode": "reading",
            "display_mode": "dots",
            "rows": 6,
            "columns": 7,
            "emphasis": "rows"
          },
          {
            "tangible_id": "equation_builder_rows",
            "description": "Equation builder showing 6 × 7 = 42.",
            "tangible_type": "equation_builder",
            "template": [
              "__",
              "×",
              "__",
              "=",
              "__"
            ],
            "style": "equation"
          }
        ],
        "id": "s1_2_dual_expression_building_b4"
      },
      {
        "type": "scene",
        "method": "update",
        "tangible_id": "arrays_6x7",
        "params": {
          "emphasis": "columns",
          "description": "Row emphasis clears. Column emphasis applies — 7 vertical bands highlighted."
        },
        "id": "s1_2_dual_expression_building_b5",
        "_notion_block_id": "33e5917e-ac52-81e0-84b5-de29bc6d72f6"
      },
      {
        "type": "scene",
        "method": "update",
        "tangible_id": "equation_builder_rows",
        "params": {
          "clear_slots": true,
          "description": "Equation builder slots clear, ready for new input."
        },
        "id": "s1_2_dual_expression_building_b6",
        "_notion_block_id": "33e5917e-ac52-81d5-9ae4-ea69f2697406"
      },
      {
        "type": "dialogue",
        "text": "Now the columns. Build the column equation.",
        "id": "s1_2_dual_expression_building_b7",
        "_notion_block_id": "33e5917e-ac52-8191-8f03-f4ebab265a40"
      },
      {
        "type": "prompt",
        "text": "Build the equation for the columns.",
        "tool": "place_tile",
        "target": "equation_builder_rows",
        "validator": [
          {
            "condition_id": "correct",
            "condition": {
              "placed": {
                "groups": 7,
                "items": 6,
                "total": 42
              }
            },
            "description": "Student placed 7 × 6 = 42, correct",
            "is_correct": true,
            "beats": [
              {
                "type": "dialogue",
                "text": "That's it. 7 columns of 6. 7 times 6 equals 42. Same product.",
                "id": "s1_2_dual_expression_building_b8_v0_b0"
              }
            ]
          },
          {
            "condition": {
              "incorrect_count": 1
            },
            "description": "Student placed incorrect tiles on first attempt for column equation",
            "is_correct": false,
            "beats": [
              {
                "type": "dialogue",
                "text": "Check the columns — the vertical bands.",
                "id": "s1_2_dual_expression_building_b8_v1_b0"
              }
            ]
          },
          {
            "condition": {
              "incorrect_count": 2
            },
            "description": "Student placed incorrect tiles on second attempt for column equation",
            "is_correct": false,
            "beats": [
              {
                "type": "scene",
                "method": "update",
                "tangible_id": "arrays_6x7",
                "params": {
                  "description": "One column pulses to show what counts as a column."
                },
                "id": "s1_2_dual_expression_building_b8_v2_b0"
              },
              {
                "type": "dialogue",
                "text": "Here's a hint: the columns are highlighted. Count them. There are 7 columns. Each column has 6 dots.",
                "id": "s1_2_dual_expression_building_b8_v2_b1"
              }
            ]
          },
          {
            "condition": {},
            "description": "Student placed incorrect tiles three or more times. System models the answer.",
            "is_correct": false,
            "beats": [
              {
                "type": "scene",
                "method": "animate",
                "tangible_id": "equation_builder_rows",
                "params": {
                  "event": "place_tiles",
                  "status": "confirmed",
                  "description": "System places tiles 7, 6, and 42 into slots.",
                  "tiles": [
                    7,
                    6,
                    42
                  ]
                },
                "id": "s1_2_dual_expression_building_b8_v3_b0"
              },
              {
                "type": "dialogue",
                "text": "Here, let me walk you through this one. I count the columns: 7. I count the dots in one column: 6. So the equation is 7 times 6 equals 42. The product stays the same.",
                "id": "s1_2_dual_expression_building_b8_v3_b1"
              }
            ]
          }
        ],
        "id": "s1_2_dual_expression_building_b8",
        "_notion_block_id": "33e5917e-ac52-8190-ac73-cafc5d3292fd"
      },
      {
        "type": "current_scene",
        "elements": [
          {
            "tangible_id": "arrays_6x7",
            "description": "6×7 dot array with column emphasis — 7 vertical bands highlighted.",
            "tangible_type": "arrays",
            "mode": "reading",
            "display_mode": "dots",
            "rows": 6,
            "columns": 7,
            "emphasis": "columns"
          },
          {
            "tangible_id": "equation_builder_rows",
            "description": "Equation builder showing 7 × 6 = 42.",
            "tangible_type": "equation_builder",
            "template": [
              "__",
              "×",
              "__",
              "=",
              "__"
            ],
            "style": "equation"
          }
        ],
        "id": "s1_2_dual_expression_building_b9"
      }
    ],
    "_generated_at": "2026-04-10T21:22:37.446470+00:00",
    "_notion_block_id": "33e5917e-ac52-81e0-bfed-e7f7b48ff246"
  },
  {
    "id": "s1_3_rotation_prediction_identify",
    "beats": [
      {
        "type": "scene",
        "method": "add",
        "tangible_id": "array_2x8",
        "tangible_type": "arrays",
        "params": {
          "mode": "read",
          "rows": 2,
          "items_per_row": 8,
          "display_mode": "dots",
          "description": "2×8 dot array appears on screen."
        },
        "id": "s1_3_rotation_prediction_identify_b0",
        "_notion_block_id": "33e5917e-ac52-8149-a83c-fa4d52117109"
      },
      {
        "type": "scene",
        "method": "animate",
        "tangible_id": "array_2x8",
        "params": {
          "event": "highlight_rows",
          "status": "confirmed",
          "description": "System highlights rows sequentially."
        },
        "id": "s1_3_rotation_prediction_identify_b1",
        "_notion_block_id": "33e5917e-ac52-816d-bf85-e23f99dd5089"
      },
      {
        "type": "dialogue",
        "text": "2 rows of 8. That's 2 times 8 equals 16. If I rotate this array, what will the new row expression be?",
        "id": "s1_3_rotation_prediction_identify_b2",
        "_notion_block_id": "33e5917e-ac52-8194-9dab-e72dcbe7fc0a"
      },
      {
        "type": "prompt",
        "text": "After rotation, what will the row expression be?",
        "tool": "multiple_choice",
        "options": [
          "8 × 2",
          "2 × 8",
          "16 × 2",
          "8 + 2"
        ],
        "validator": [
          {
            "condition_id": "correct",
            "condition": {
              "selected": "8 × 2"
            },
            "description": "Student selected 8 × 2, correct",
            "is_correct": true,
            "beats": [
              {
                "type": "dialogue",
                "text": "That's it. 8 times 2. After rotating, 8 rows of 2.",
                "id": "s1_3_rotation_prediction_identify_b3_v0_b0"
              }
            ]
          },
          {
            "condition": {
              "selected": "2 × 8"
            },
            "description": "Student selected 2 × 8: did not recognize that rotation changes the row expression",
            "is_correct": false,
            "beats": [
              {
                "type": "scene",
                "method": "update",
                "tangible_id": "array_2x8",
                "params": {
                  "description": "Array highlights to show current orientation: 2 rows of 8."
                },
                "id": "s1_3_rotation_prediction_identify_b3_v1_b0"
              },
              {
                "type": "dialogue",
                "text": "That's the expression now, before rotating. When we rotate, rows become columns and columns become rows. What will the new row count be?",
                "id": "s1_3_rotation_prediction_identify_b3_v1_b1"
              }
            ]
          },
          {
            "condition": {
              "selected": "16 × 2"
            },
            "description": "Student selected 16 × 2: used the total instead of the row structure",
            "is_correct": false,
            "beats": [
              {
                "type": "scene",
                "method": "update",
                "tangible_id": "array_2x8",
                "params": {
                  "description": "Array highlights to emphasize row structure."
                },
                "id": "s1_3_rotation_prediction_identify_b3_v2_b0"
              },
              {
                "type": "dialogue",
                "text": "16 is the total dots, not the number of rows. After rotation, the 8 columns will become 8 rows. How many dots will be in each row?",
                "id": "s1_3_rotation_prediction_identify_b3_v2_b1"
              }
            ]
          },
          {
            "condition": {
              "selected": "8 + 2"
            },
            "description": "Student selected 8 + 2: used addition instead of multiplication",
            "is_correct": false,
            "beats": [
              {
                "type": "scene",
                "method": "update",
                "tangible_id": "array_2x8",
                "params": {
                  "description": "Array highlights rows to show multiplication structure."
                },
                "id": "s1_3_rotation_prediction_identify_b3_v3_b0"
              },
              {
                "type": "dialogue",
                "text": "Arrays use multiplication, not addition. We count rows times dots per row. After rotation, we'll have 8 rows. How many dots will each row have?",
                "id": "s1_3_rotation_prediction_identify_b3_v3_b1"
              }
            ]
          },
          {
            "condition": {},
            "description": "Student answered incorrectly. System models the correct answer.",
            "is_correct": false,
            "beats": [
              {
                "type": "scene",
                "method": "animate",
                "tangible_id": "array_2x8",
                "params": {
                  "event": "rotate_90_clockwise",
                  "status": "confirmed",
                  "description": "Array rotates 90 degrees clockwise, becoming 8×2."
                },
                "id": "s1_3_rotation_prediction_identify_b3_v4_b0"
              },
              {
                "type": "scene",
                "method": "update",
                "tangible_id": "array_2x8",
                "params": {
                  "rows": 8,
                  "items_per_row": 2,
                  "description": "Array now shows 8 rows of 2 dots each."
                },
                "id": "s1_3_rotation_prediction_identify_b3_v4_b1"
              },
              {
                "type": "dialogue",
                "text": "Let me show you how rotation works. The 2 rows become 2 columns. The 8 columns become 8 rows. Now we have 8 rows of 2 dots. The row expression is 8 times 2. Rotation switches the numbers in the multiplication.",
                "id": "s1_3_rotation_prediction_identify_b3_v4_b2"
              }
            ]
          }
        ],
        "id": "s1_3_rotation_prediction_identify_b3",
        "_notion_block_id": "33e5917e-ac52-81a8-acf3-c20cfb9fe344"
      },
      {
        "type": "current_scene",
        "elements": [
          {
            "tangible_id": "array_2x8",
            "description": "2×8 dot array displayed. Rows highlighted. Multiple choice tool active.",
            "tangible_type": "arrays",
            "mode": "read",
            "rows": 2,
            "items_per_row": 8,
            "display_mode": "dots"
          }
        ],
        "id": "s1_3_rotation_prediction_identify_b4"
      },
      {
        "type": "scene",
        "method": "animate",
        "tangible_id": "array_2x8",
        "params": {
          "event": "rotate_90_clockwise",
          "status": "confirmed",
          "description": "Array rotates 90 degrees clockwise, becoming 8×2 array."
        },
        "id": "s1_3_rotation_prediction_identify_b5",
        "_notion_block_id": "33e5917e-ac52-81f5-9fa6-ddeef228d25f"
      },
      {
        "type": "scene",
        "method": "update",
        "tangible_id": "array_2x8",
        "params": {
          "rows": 8,
          "items_per_row": 2,
          "description": "Array now shows 8 rows of 2 dots each after rotation."
        },
        "id": "s1_3_rotation_prediction_identify_b6",
        "_notion_block_id": "33e5917e-ac52-81d1-b6ed-dc3c6fd07aee"
      },
      {
        "type": "current_scene",
        "elements": [
          {
            "tangible_id": "array_2x8",
            "description": "8×2 dot array after rotation. 8 rows of 2 dots each.",
            "tangible_type": "arrays",
            "mode": "read",
            "rows": 8,
            "items_per_row": 2,
            "display_mode": "dots"
          }
        ],
        "id": "s1_3_rotation_prediction_identify_b7"
      }
    ],
    "_generated_at": "2026-04-10T21:22:48.941257+00:00",
    "_notion_block_id": "33e5917e-ac52-8158-8ad1-d8f94507ad07"
  },
  {
    "id": "s1_4_equivalence_discrimination_compare",
    "beats": [
      {
        "type": "scene",
        "method": "add",
        "tangible_id": "array_reference",
        "tangible_type": "arrays",
        "params": {
          "mode": "reading",
          "rows": 5,
          "items_per_row": 6,
          "item_type": "dots",
          "description": "5×6 dot array displayed as reference. 5 rows of 6 dots. 30 dots total."
        },
        "id": "s1_4_equivalence_discrimination_compare_b0",
        "_notion_block_id": "33e5917e-ac52-81bf-a2c3-fa4e16424c5c"
      },
      {
        "type": "scene",
        "method": "add",
        "tangible_id": "mc_options",
        "tangible_type": "multiple_choice_options",
        "params": {
          "description": "Four dot arrays displayed as answer options. A) 3×10 array. B) 6×5 array. C) 10×3 array. D) 2×15 array. All arrays show 30 dots total."
        },
        "id": "s1_4_equivalence_discrimination_compare_b1",
        "_notion_block_id": "33e5917e-ac52-81ca-9fca-ca09a2de4a39"
      },
      {
        "type": "dialogue",
        "text": "Here's an array: 5 rows of 6. That's 30 dots. These four arrays all have 30 dots too. Which one is the same array, just rotated?",
        "id": "s1_4_equivalence_discrimination_compare_b2",
        "_notion_block_id": "33e5917e-ac52-81c1-b5d5-e4ad1e47fbbd"
      },
      {
        "type": "prompt",
        "text": "Which array is the same as 5 times 6, just rotated?",
        "tool": "multiple_choice",
        "options": [
          "A) 3 × 10",
          "B) 6 × 5",
          "C) 10 × 3",
          "D) 2 × 15"
        ],
        "validator": [
          {
            "condition_id": "correct",
            "condition": {
              "selected": "B) 6 × 5"
            },
            "description": "Student selected B) 6 × 5, correct rotation of 5×6",
            "is_correct": true,
            "beats": [
              {
                "type": "scene",
                "method": "update",
                "tangible_id": "mc_options",
                "params": {
                  "highlight_option": "B) 6 × 5",
                  "description": "Option B) 6 × 5 highlights to confirm selection."
                },
                "id": "s1_4_equivalence_discrimination_compare_b3_v0_b0"
              },
              {
                "type": "dialogue",
                "text": "Right. 6 rows of 5. That's 5 rows of 6, just turned. Same dots, same product.",
                "id": "s1_4_equivalence_discrimination_compare_b3_v0_b1"
              }
            ]
          },
          {
            "condition": {
              "selected": "A) 3 × 10"
            },
            "description": "Student selected A) 3 × 10, which has 30 dots but different row and column structure",
            "is_correct": false,
            "beats": [
              {
                "type": "scene",
                "method": "update",
                "tangible_id": "mc_options",
                "params": {
                  "highlight_option": "A) 3 × 10",
                  "description": "Option A) 3 × 10 highlights."
                },
                "id": "s1_4_equivalence_discrimination_compare_b3_v1_b0"
              },
              {
                "type": "dialogue",
                "text": "That array has 30 dots, but look at the rows. The reference has 5 rows. When you rotate, the rows become columns.",
                "id": "s1_4_equivalence_discrimination_compare_b3_v1_b1"
              }
            ]
          },
          {
            "condition": {
              "selected": "C) 10 × 3"
            },
            "description": "Student selected C) 10 × 3, which has 30 dots but different row and column structure",
            "is_correct": false,
            "beats": [
              {
                "type": "scene",
                "method": "update",
                "tangible_id": "mc_options",
                "params": {
                  "highlight_option": "C) 10 × 3",
                  "description": "Option C) 10 × 3 highlights."
                },
                "id": "s1_4_equivalence_discrimination_compare_b3_v2_b0"
              },
              {
                "type": "dialogue",
                "text": "This array has 30 dots, but the row and column counts are different. When you rotate 5 rows of 6, you get 6 rows of 5.",
                "id": "s1_4_equivalence_discrimination_compare_b3_v2_b1"
              }
            ]
          },
          {
            "condition": {
              "selected": "D) 2 × 15"
            },
            "description": "Student selected D) 2 × 15, which has 30 dots but completely different structure",
            "is_correct": false,
            "beats": [
              {
                "type": "scene",
                "method": "update",
                "tangible_id": "mc_options",
                "params": {
                  "highlight_option": "D) 2 × 15",
                  "description": "Option D) 2 × 15 highlights."
                },
                "id": "s1_4_equivalence_discrimination_compare_b3_v3_b0"
              },
              {
                "type": "dialogue",
                "text": "That array has 30 dots, but rotating doesn't change the numbers that much. If you turn 5 rows of 6, the 5 and the 6 swap places.",
                "id": "s1_4_equivalence_discrimination_compare_b3_v3_b1"
              }
            ]
          },
          {
            "condition": {},
            "description": "Student answered incorrectly. System models the correct answer.",
            "is_correct": false,
            "beats": [
              {
                "type": "scene",
                "method": "animate",
                "tangible_id": "array_reference",
                "params": {
                  "event": "rotate_90",
                  "status": "confirmed",
                  "description": "Reference array rotates 90 degrees, transforming from 5 rows of 6 to 6 rows of 5."
                },
                "id": "s1_4_equivalence_discrimination_compare_b3_v4_b0"
              },
              {
                "type": "dialogue",
                "text": "Let me show you how this works. When I rotate the reference array, the 5 rows become 5 columns. The 6 dots in each row become 6 rows. So 5 rows of 6 becomes 6 rows of 5. The answer is B) 6 × 5. That is the rotated version of the reference array.",
                "id": "s1_4_equivalence_discrimination_compare_b3_v4_b1"
              }
            ]
          }
        ],
        "id": "s1_4_equivalence_discrimination_compare_b3",
        "_notion_block_id": "33e5917e-ac52-81b1-8070-f51abcae68b1"
      },
      {
        "type": "current_scene",
        "elements": [
          {
            "tangible_id": "array_reference",
            "description": "5×6 dot array displayed as reference. 5 rows of 6 dots.",
            "tangible_type": "arrays",
            "mode": "reading",
            "rows": 5,
            "items_per_row": 6,
            "item_type": "dots"
          },
          {
            "tangible_id": "mc_options",
            "description": "Four dot arrays displayed as options: A) 3×10, B) 6×5, C) 10×3, D) 2×15. All showing 30 dots.",
            "tangible_type": "multiple_choice_options"
          }
        ],
        "id": "s1_4_equivalence_discrimination_compare_b4"
      }
    ],
    "_generated_at": "2026-04-10T21:22:59.859269+00:00",
    "_notion_block_id": "33e5917e-ac52-81ca-a2a4-df02be2ea9c3"
  },
  {
    "id": "s1_5_exit_check_closure",
    "type": "transition",
    "beats": [
      {
        "type": "dialogue",
        "text": "You're ready. Let's practice.",
        "id": "s1_5_exit_check_closure_b0",
        "_notion_block_id": "33e5917e-ac52-819e-894d-c76334521701"
      },
      {
        "type": "current_scene",
        "elements": [],
        "id": "s1_5_exit_check_closure_b1"
      }
    ],
    "_generated_at": "2026-04-10T21:23:02.103777+00:00",
    "_notion_block_id": "33e5917e-ac52-8158-aed5-d15ef2f4b286"
  }
]
