[
  {
    "object": "block",
    "id": "3485917e-ac52-8125-b381-de7ced3374cc",
    "parent": {
      "type": "page_id",
      "page_id": "3485917e-ac52-8183-8657-cabc4a8e078c"
    },
    "created_time": "2026-04-20T17:01:00.000Z",
    "last_edited_time": "2026-04-20T17:01:00.000Z",
    "created_by": {
      "object": "user",
      "id": "31a5917e-ac52-8155-8199-00271e06ffde"
    },
    "last_edited_by": {
      "object": "user",
      "id": "31a5917e-ac52-8155-8199-00271e06ffde"
    },
    "has_children": false,
    "in_trash": false,
    "type": "callout",
    "callout": {
      "rich_text": [
        {
          "type": "text",
          "text": {
            "content": "Toggle all: Ctrl+Alt+T / Cmd+Opt+T  •  {word} = vocab highlight — dialogue only",
            "link": null
          },
          "annotations": {
            "bold": false,
            "italic": false,
            "strikethrough": false,
            "underline": false,
            "code": false,
            "color": "default"
          },
          "plain_text": "Toggle all: Ctrl+Alt+T / Cmd+Opt+T  •  {word} = vocab highlight — dialogue only",
          "href": null
        }
      ],
      "icon": {
        "type": "emoji",
        "emoji": "💡"
      },
      "color": "yellow_background"
    },
    "archived": false
  },
  {
    "object": "block",
    "id": "3485917e-ac52-81ea-92f6-f7e7bf71475c",
    "parent": {
      "type": "page_id",
      "page_id": "3485917e-ac52-8183-8657-cabc4a8e078c"
    },
    "created_time": "2026-04-20T17:01:00.000Z",
    "last_edited_time": "2026-04-20T17:01:00.000Z",
    "created_by": {
      "object": "user",
      "id": "31a5917e-ac52-8155-8199-00271e06ffde"
    },
    "last_edited_by": {
      "object": "user",
      "id": "31a5917e-ac52-8155-8199-00271e06ffde"
    },
    "has_children": false,
    "in_trash": false,
    "type": "divider",
    "divider": {},
    "archived": false
  },
  {
    "object": "block",
    "id": "3485917e-ac52-811f-85d9-fcde17fd3a4f",
    "parent": {
      "type": "page_id",
      "page_id": "3485917e-ac52-8183-8657-cabc4a8e078c"
    },
    "created_time": "2026-04-20T17:01:00.000Z",
    "last_edited_time": "2026-04-20T17:01:00.000Z",
    "created_by": {
      "object": "user",
      "id": "31a5917e-ac52-8155-8199-00271e06ffde"
    },
    "last_edited_by": {
      "object": "user",
      "id": "31a5917e-ac52-8155-8199-00271e06ffde"
    },
    "has_children": false,
    "in_trash": false,
    "type": "heading_2",
    "heading_2": {
      "rich_text": [
        {
          "type": "text",
          "text": {
            "content": "1.1  Equation Building Callback Activation  [s1_1_equation_building_callback_activation]",
            "link": null
          },
          "annotations": {
            "bold": false,
            "italic": false,
            "strikethrough": false,
            "underline": false,
            "code": false,
            "color": "default"
          },
          "plain_text": "1.1  Equation Building Callback Activation  [s1_1_equation_building_callback_activation]",
          "href": null
        }
      ],
      "is_toggleable": false,
      "color": "default"
    },
    "archived": false
  },
  {
    "object": "block",
    "id": "3485917e-ac52-8136-bafb-f999020a6acc",
    "parent": {
      "type": "page_id",
      "page_id": "3485917e-ac52-8183-8657-cabc4a8e078c"
    },
    "created_time": "2026-04-20T17:01:00.000Z",
    "last_edited_time": "2026-04-20T17:01:00.000Z",
    "created_by": {
      "object": "user",
      "id": "31a5917e-ac52-8155-8199-00271e06ffde"
    },
    "last_edited_by": {
      "object": "user",
      "id": "31a5917e-ac52-8155-8199-00271e06ffde"
    },
    "has_children": false,
    "in_trash": false,
    "type": "callout",
    "callout": {
      "rich_text": [
        {
          "type": "text",
          "text": {
            "content": "Equal groups visual appears: 5 bags with 2 items each.",
            "link": null
          },
          "annotations": {
            "bold": false,
            "italic": false,
            "strikethrough": false,
            "underline": false,
            "code": false,
            "color": "default"
          },
          "plain_text": "Equal groups visual appears: 5 bags with 2 items each.",
          "href": null
        }
      ],
      "icon": {
        "type": "emoji",
        "emoji": "🎬"
      },
      "color": "default"
    },
    "archived": false
  },
  {
    "object": "block",
    "id": "3485917e-ac52-81db-845c-e58f9f21ac21",
    "parent": {
      "type": "page_id",
      "page_id": "3485917e-ac52-8183-8657-cabc4a8e078c"
    },
    "created_time": "2026-04-20T17:01:00.000Z",
    "last_edited_time": "2026-04-20T17:01:00.000Z",
    "created_by": {
      "object": "user",
      "id": "31a5917e-ac52-8155-8199-00271e06ffde"
    },
    "last_edited_by": {
      "object": "user",
      "id": "31a5917e-ac52-8155-8199-00271e06ffde"
    },
    "has_children": false,
    "in_trash": false,
    "type": "callout",
    "callout": {
      "rich_text": [
        {
          "type": "text",
          "text": {
            "content": "Equation builder appears alongside with full equation template and tile palette 1 through 10.",
            "link": null
          },
          "annotations": {
            "bold": false,
            "italic": false,
            "strikethrough": false,
            "underline": false,
            "code": false,
            "color": "default"
          },
          "plain_text": "Equation builder appears alongside with full equation template and tile palette 1 through 10.",
          "href": null
        }
      ],
      "icon": {
        "type": "emoji",
        "emoji": "🎬"
      },
      "color": "default"
    },
    "archived": false
  },
  {
    "object": "block",
    "id": "3485917e-ac52-815c-9ba4-dcf081c3a93f",
    "parent": {
      "type": "page_id",
      "page_id": "3485917e-ac52-8183-8657-cabc4a8e078c"
    },
    "created_time": "2026-04-20T17:01:00.000Z",
    "last_edited_time": "2026-04-20T17:01:00.000Z",
    "created_by": {
      "object": "user",
      "id": "31a5917e-ac52-8155-8199-00271e06ffde"
    },
    "last_edited_by": {
      "object": "user",
      "id": "31a5917e-ac52-8155-8199-00271e06ffde"
    },
    "has_children": false,
    "in_trash": false,
    "type": "callout",
    "callout": {
      "rich_text": [
        {
          "type": "text",
          "text": {
            "content": "\"Let's warm up. You've been building equations. Let's make sure you've still got it. Build the equation for this picture.\"",
            "link": null
          },
          "annotations": {
            "bold": false,
            "italic": false,
            "strikethrough": false,
            "underline": false,
            "code": false,
            "color": "default"
          },
          "plain_text": "\"Let's warm up. You've been building equations. Let's make sure you've still got it. Build the equation for this picture.\"",
          "href": null
        }
      ],
      "icon": {
        "type": "emoji",
        "emoji": "💬"
      },
      "color": "default"
    },
    "archived": false
  },
  {
    "object": "block",
    "id": "3485917e-ac52-81d1-bc22-e09fe65e15ba",
    "parent": {
      "type": "page_id",
      "page_id": "3485917e-ac52-8183-8657-cabc4a8e078c"
    },
    "created_time": "2026-04-20T17:01:00.000Z",
    "last_edited_time": "2026-04-20T17:01:00.000Z",
    "created_by": {
      "object": "user",
      "id": "31a5917e-ac52-8155-8199-00271e06ffde"
    },
    "last_edited_by": {
      "object": "user",
      "id": "31a5917e-ac52-8155-8199-00271e06ffde"
    },
    "has_children": false,
    "in_trash": false,
    "type": "callout",
    "callout": {
      "rich_text": [
        {
          "type": "text",
          "text": {
            "content": "tool: place_tile  target: equation_builder_warmup\n\"Build the equation for this picture.\"",
            "link": null
          },
          "annotations": {
            "bold": false,
            "italic": false,
            "strikethrough": false,
            "underline": false,
            "code": false,
            "color": "default"
          },
          "plain_text": "tool: place_tile  target: equation_builder_warmup\n\"Build the equation for this picture.\"",
          "href": null
        }
      ],
      "icon": {
        "type": "emoji",
        "emoji": "❔"
      },
      "color": "default"
    },
    "archived": false
  },
  {
    "object": "block",
    "id": "3485917e-ac52-811e-a7c7-cb4d09948e24",
    "parent": {
      "type": "page_id",
      "page_id": "3485917e-ac52-8183-8657-cabc4a8e078c"
    },
    "created_time": "2026-04-20T17:01:00.000Z",
    "last_edited_time": "2026-04-20T17:01:00.000Z",
    "created_by": {
      "object": "user",
      "id": "31a5917e-ac52-8155-8199-00271e06ffde"
    },
    "last_edited_by": {
      "object": "user",
      "id": "31a5917e-ac52-8155-8199-00271e06ffde"
    },
    "has_children": true,
    "in_trash": false,
    "type": "toggle",
    "toggle": {
      "rich_text": [
        {
          "type": "text",
          "text": {
            "content": "✅ Student placed 5 × 2 = 10, correct",
            "link": null
          },
          "annotations": {
            "bold": false,
            "italic": false,
            "strikethrough": false,
            "underline": false,
            "code": false,
            "color": "default"
          },
          "plain_text": "✅ Student placed 5 × 2 = 10, correct",
          "href": null
        }
      ],
      "color": "default",
      "children": [
        {
          "object": "block",
          "id": "3485917e-ac52-81fc-a459-f4134460c846",
          "parent": {
            "type": "block_id",
            "block_id": "3485917e-ac52-811e-a7c7-cb4d09948e24"
          },
          "created_time": "2026-04-20T17:01:00.000Z",
          "last_edited_time": "2026-04-20T17:01:00.000Z",
          "created_by": {
            "object": "user",
            "id": "31a5917e-ac52-8155-8199-00271e06ffde"
          },
          "last_edited_by": {
            "object": "user",
            "id": "31a5917e-ac52-8155-8199-00271e06ffde"
          },
          "has_children": false,
          "in_trash": false,
          "type": "callout",
          "callout": {
            "rich_text": [
              {
                "type": "text",
                "text": {
                  "content": "\"Right. 5 groups of 2. 5 times 2 equals 10. You know how to build equations.\"",
                  "link": null
                },
                "annotations": {
                  "bold": false,
                  "italic": false,
                  "strikethrough": false,
                  "underline": false,
                  "code": false,
                  "color": "default"
                },
                "plain_text": "\"Right. 5 groups of 2. 5 times 2 equals 10. You know how to build equations.\"",
                "href": null
              }
            ],
            "icon": {
              "type": "emoji",
              "emoji": "💬"
            },
            "color": "default"
          },
          "archived": false
        }
      ]
    },
    "archived": false
  },
  {
    "object": "block",
    "id": "3485917e-ac52-8191-964a-def25eb6a140",
    "parent": {
      "type": "page_id",
      "page_id": "3485917e-ac52-8183-8657-cabc4a8e078c"
    },
    "created_time": "2026-04-20T17:01:00.000Z",
    "last_edited_time": "2026-04-20T17:01:00.000Z",
    "created_by": {
      "object": "user",
      "id": "31a5917e-ac52-8155-8199-00271e06ffde"
    },
    "last_edited_by": {
      "object": "user",
      "id": "31a5917e-ac52-8155-8199-00271e06ffde"
    },
    "has_children": true,
    "in_trash": false,
    "type": "toggle",
    "toggle": {
      "rich_text": [
        {
          "type": "text",
          "text": {
            "content": "❌ Student reversed groups and items (2 × 5) or wrote 10 as groups",
            "link": null
          },
          "annotations": {
            "bold": false,
            "italic": false,
            "strikethrough": false,
            "underline": false,
            "code": false,
            "color": "default"
          },
          "plain_text": "❌ Student reversed groups and items (2 × 5) or wrote 10 as groups",
          "href": null
        }
      ],
      "color": "default",
      "children": [
        {
          "object": "block",
          "id": "3485917e-ac52-8116-8f86-d428b067057f",
          "parent": {
            "type": "block_id",
            "block_id": "3485917e-ac52-8191-964a-def25eb6a140"
          },
          "created_time": "2026-04-20T17:01:00.000Z",
          "last_edited_time": "2026-04-20T17:01:00.000Z",
          "created_by": {
            "object": "user",
            "id": "31a5917e-ac52-8155-8199-00271e06ffde"
          },
          "last_edited_by": {
            "object": "user",
            "id": "31a5917e-ac52-8155-8199-00271e06ffde"
          },
          "has_children": false,
          "in_trash": false,
          "type": "callout",
          "callout": {
            "rich_text": [
              {
                "type": "text",
                "text": {
                  "content": "The 5 bags highlight to show groups.",
                  "link": null
                },
                "annotations": {
                  "bold": false,
                  "italic": false,
                  "strikethrough": false,
                  "underline": false,
                  "code": false,
                  "color": "default"
                },
                "plain_text": "The 5 bags highlight to show groups.",
                "href": null
              }
            ],
            "icon": {
              "type": "emoji",
              "emoji": "🎬"
            },
            "color": "default"
          },
          "archived": false
        },
        {
          "object": "block",
          "id": "3485917e-ac52-814a-9492-f0ae7982ccdf",
          "parent": {
            "type": "block_id",
            "block_id": "3485917e-ac52-8191-964a-def25eb6a140"
          },
          "created_time": "2026-04-20T17:01:00.000Z",
          "last_edited_time": "2026-04-20T17:01:00.000Z",
          "created_by": {
            "object": "user",
            "id": "31a5917e-ac52-8155-8199-00271e06ffde"
          },
          "last_edited_by": {
            "object": "user",
            "id": "31a5917e-ac52-8155-8199-00271e06ffde"
          },
          "has_children": false,
          "in_trash": false,
          "type": "callout",
          "callout": {
            "rich_text": [
              {
                "type": "text",
                "text": {
                  "content": "\"Count the bags. That's your first number, the groups. Then count what's in one bag. That's your second number.\"",
                  "link": null
                },
                "annotations": {
                  "bold": false,
                  "italic": false,
                  "strikethrough": false,
                  "underline": false,
                  "code": false,
                  "color": "default"
                },
                "plain_text": "\"Count the bags. That's your first number, the groups. Then count what's in one bag. That's your second number.\"",
                "href": null
              }
            ],
            "icon": {
              "type": "emoji",
              "emoji": "💬"
            },
            "color": "default"
          },
          "archived": false
        }
      ]
    },
    "archived": false
  },
  {
    "object": "block",
    "id": "3485917e-ac52-8135-a095-c1108da7f1ff",
    "parent": {
      "type": "page_id",
      "page_id": "3485917e-ac52-8183-8657-cabc4a8e078c"
    },
    "created_time": "2026-04-20T17:01:00.000Z",
    "last_edited_time": "2026-04-20T17:01:00.000Z",
    "created_by": {
      "object": "user",
      "id": "31a5917e-ac52-8155-8199-00271e06ffde"
    },
    "last_edited_by": {
      "object": "user",
      "id": "31a5917e-ac52-8155-8199-00271e06ffde"
    },
    "has_children": true,
    "in_trash": false,
    "type": "toggle",
    "toggle": {
      "rich_text": [
        {
          "type": "text",
          "text": {
            "content": "❌ Student built an incorrect equation on first attempt",
            "link": null
          },
          "annotations": {
            "bold": false,
            "italic": false,
            "strikethrough": false,
            "underline": false,
            "code": false,
            "color": "default"
          },
          "plain_text": "❌ Student built an incorrect equation on first attempt",
          "href": null
        }
      ],
      "color": "default",
      "children": [
        {
          "object": "block",
          "id": "3485917e-ac52-81d4-b5f1-e1a051ed03e8",
          "parent": {
            "type": "block_id",
            "block_id": "3485917e-ac52-8135-a095-c1108da7f1ff"
          },
          "created_time": "2026-04-20T17:01:00.000Z",
          "last_edited_time": "2026-04-20T17:01:00.000Z",
          "created_by": {
            "object": "user",
            "id": "31a5917e-ac52-8155-8199-00271e06ffde"
          },
          "last_edited_by": {
            "object": "user",
            "id": "31a5917e-ac52-8155-8199-00271e06ffde"
          },
          "has_children": false,
          "in_trash": false,
          "type": "callout",
          "callout": {
            "rich_text": [
              {
                "type": "text",
                "text": {
                  "content": "\"Not quite. Count the bags, then what's inside one bag.\"",
                  "link": null
                },
                "annotations": {
                  "bold": false,
                  "italic": false,
                  "strikethrough": false,
                  "underline": false,
                  "code": false,
                  "color": "default"
                },
                "plain_text": "\"Not quite. Count the bags, then what's inside one bag.\"",
                "href": null
              }
            ],
            "icon": {
              "type": "emoji",
              "emoji": "💬"
            },
            "color": "default"
          },
          "archived": false
        }
      ]
    },
    "archived": false
  },
  {
    "object": "block",
    "id": "3485917e-ac52-819c-ae08-c54bd81b17a3",
    "parent": {
      "type": "page_id",
      "page_id": "3485917e-ac52-8183-8657-cabc4a8e078c"
    },
    "created_time": "2026-04-20T17:01:00.000Z",
    "last_edited_time": "2026-04-20T17:01:00.000Z",
    "created_by": {
      "object": "user",
      "id": "31a5917e-ac52-8155-8199-00271e06ffde"
    },
    "last_edited_by": {
      "object": "user",
      "id": "31a5917e-ac52-8155-8199-00271e06ffde"
    },
    "has_children": true,
    "in_trash": false,
    "type": "toggle",
    "toggle": {
      "rich_text": [
        {
          "type": "text",
          "text": {
            "content": "❌ Student built an incorrect equation on second attempt",
            "link": null
          },
          "annotations": {
            "bold": false,
            "italic": false,
            "strikethrough": false,
            "underline": false,
            "code": false,
            "color": "default"
          },
          "plain_text": "❌ Student built an incorrect equation on second attempt",
          "href": null
        }
      ],
      "color": "default",
      "children": [
        {
          "object": "block",
          "id": "3485917e-ac52-81dc-9068-dd74acf21ed0",
          "parent": {
            "type": "block_id",
            "block_id": "3485917e-ac52-819c-ae08-c54bd81b17a3"
          },
          "created_time": "2026-04-20T17:01:00.000Z",
          "last_edited_time": "2026-04-20T17:01:00.000Z",
          "created_by": {
            "object": "user",
            "id": "31a5917e-ac52-8155-8199-00271e06ffde"
          },
          "last_edited_by": {
            "object": "user",
            "id": "31a5917e-ac52-8155-8199-00271e06ffde"
          },
          "has_children": false,
          "in_trash": false,
          "type": "callout",
          "callout": {
            "rich_text": [
              {
                "type": "text",
                "text": {
                  "content": "The 5 bags highlight.",
                  "link": null
                },
                "annotations": {
                  "bold": false,
                  "italic": false,
                  "strikethrough": false,
                  "underline": false,
                  "code": false,
                  "color": "default"
                },
                "plain_text": "The 5 bags highlight.",
                "href": null
              }
            ],
            "icon": {
              "type": "emoji",
              "emoji": "🎬"
            },
            "color": "default"
          },
          "archived": false
        },
        {
          "object": "block",
          "id": "3485917e-ac52-8128-b420-e05445391fcf",
          "parent": {
            "type": "block_id",
            "block_id": "3485917e-ac52-819c-ae08-c54bd81b17a3"
          },
          "created_time": "2026-04-20T17:01:00.000Z",
          "last_edited_time": "2026-04-20T17:01:00.000Z",
          "created_by": {
            "object": "user",
            "id": "31a5917e-ac52-8155-8199-00271e06ffde"
          },
          "last_edited_by": {
            "object": "user",
            "id": "31a5917e-ac52-8155-8199-00271e06ffde"
          },
          "has_children": false,
          "in_trash": false,
          "type": "callout",
          "callout": {
            "rich_text": [
              {
                "type": "text",
                "text": {
                  "content": "\"Here's what helps: the first number counts how many bags you see. The second number counts what's in one bag. What do you get?\"",
                  "link": null
                },
                "annotations": {
                  "bold": false,
                  "italic": false,
                  "strikethrough": false,
                  "underline": false,
                  "code": false,
                  "color": "default"
                },
                "plain_text": "\"Here's what helps: the first number counts how many bags you see. The second number counts what's in one bag. What do you get?\"",
                "href": null
              }
            ],
            "icon": {
              "type": "emoji",
              "emoji": "💬"
            },
            "color": "default"
          },
          "archived": false
        }
      ]
    },
    "archived": false
  },
  {
    "object": "block",
    "id": "3485917e-ac52-81a4-9025-d670e0864f05",
    "parent": {
      "type": "page_id",
      "page_id": "3485917e-ac52-8183-8657-cabc4a8e078c"
    },
    "created_time": "2026-04-20T17:01:00.000Z",
    "last_edited_time": "2026-04-20T17:01:00.000Z",
    "created_by": {
      "object": "user",
      "id": "31a5917e-ac52-8155-8199-00271e06ffde"
    },
    "last_edited_by": {
      "object": "user",
      "id": "31a5917e-ac52-8155-8199-00271e06ffde"
    },
    "has_children": true,
    "in_trash": false,
    "type": "toggle",
    "toggle": {
      "rich_text": [
        {
          "type": "text",
          "text": {
            "content": "❌ Student answered incorrectly three or more times. System models the answer.",
            "link": null
          },
          "annotations": {
            "bold": false,
            "italic": false,
            "strikethrough": false,
            "underline": false,
            "code": false,
            "color": "default"
          },
          "plain_text": "❌ Student answered incorrectly three or more times. System models the answer.",
          "href": null
        }
      ],
      "color": "default",
      "children": [
        {
          "object": "block",
          "id": "3485917e-ac52-81ec-ab95-c795bccdc461",
          "parent": {
            "type": "block_id",
            "block_id": "3485917e-ac52-81a4-9025-d670e0864f05"
          },
          "created_time": "2026-04-20T17:01:00.000Z",
          "last_edited_time": "2026-04-20T17:01:00.000Z",
          "created_by": {
            "object": "user",
            "id": "31a5917e-ac52-8155-8199-00271e06ffde"
          },
          "last_edited_by": {
            "object": "user",
            "id": "31a5917e-ac52-8155-8199-00271e06ffde"
          },
          "has_children": false,
          "in_trash": false,
          "type": "callout",
          "callout": {
            "rich_text": [
              {
                "type": "text",
                "text": {
                  "content": "System places tiles: 5 in first blank, 2 in second blank, 10 in third blank.",
                  "link": null
                },
                "annotations": {
                  "bold": false,
                  "italic": false,
                  "strikethrough": false,
                  "underline": false,
                  "code": false,
                  "color": "default"
                },
                "plain_text": "System places tiles: 5 in first blank, 2 in second blank, 10 in third blank.",
                "href": null
              }
            ],
            "icon": {
              "type": "emoji",
              "emoji": "🎬"
            },
            "color": "default"
          },
          "archived": false
        },
        {
          "object": "block",
          "id": "3485917e-ac52-8144-9879-ca95a123b071",
          "parent": {
            "type": "block_id",
            "block_id": "3485917e-ac52-81a4-9025-d670e0864f05"
          },
          "created_time": "2026-04-20T17:01:00.000Z",
          "last_edited_time": "2026-04-20T17:01:00.000Z",
          "created_by": {
            "object": "user",
            "id": "31a5917e-ac52-8155-8199-00271e06ffde"
          },
          "last_edited_by": {
            "object": "user",
            "id": "31a5917e-ac52-8155-8199-00271e06ffde"
          },
          "has_children": false,
          "in_trash": false,
          "type": "callout",
          "callout": {
            "rich_text": [
              {
                "type": "text",
                "text": {
                  "content": "\"Let me show you. I count the bags: 5 bags. That's my first number. I count what's in one bag: 2 items. That's my second number. 5 times 2 equals 10. The equation is 5 times 2 equals 10.\"",
                  "link": null
                },
                "annotations": {
                  "bold": false,
                  "italic": false,
                  "strikethrough": false,
                  "underline": false,
                  "code": false,
                  "color": "default"
                },
                "plain_text": "\"Let me show you. I count the bags: 5 bags. That's my first number. I count what's in one bag: 2 items. That's my second number. 5 times 2 equals 10. The equation is 5 times 2 equals 10.\"",
                "href": null
              }
            ],
            "icon": {
              "type": "emoji",
              "emoji": "💬"
            },
            "color": "default"
          },
          "archived": false
        }
      ]
    },
    "archived": false
  },
  {
    "object": "block",
    "id": "3485917e-ac52-81ba-8872-e071f10acb94",
    "parent": {
      "type": "page_id",
      "page_id": "3485917e-ac52-8183-8657-cabc4a8e078c"
    },
    "created_time": "2026-04-20T17:01:00.000Z",
    "last_edited_time": "2026-04-20T17:01:00.000Z",
    "created_by": {
      "object": "user",
      "id": "31a5917e-ac52-8155-8199-00271e06ffde"
    },
    "last_edited_by": {
      "object": "user",
      "id": "31a5917e-ac52-8155-8199-00271e06ffde"
    },
    "has_children": false,
    "in_trash": false,
    "type": "divider",
    "divider": {},
    "archived": false
  },
  {
    "object": "block",
    "id": "3485917e-ac52-81b4-8a3a-e1db546e4546",
    "parent": {
      "type": "page_id",
      "page_id": "3485917e-ac52-8183-8657-cabc4a8e078c"
    },
    "created_time": "2026-04-20T17:01:00.000Z",
    "last_edited_time": "2026-04-20T17:01:00.000Z",
    "created_by": {
      "object": "user",
      "id": "31a5917e-ac52-8155-8199-00271e06ffde"
    },
    "last_edited_by": {
      "object": "user",
      "id": "31a5917e-ac52-8155-8199-00271e06ffde"
    },
    "has_children": false,
    "in_trash": false,
    "type": "heading_2",
    "heading_2": {
      "rich_text": [
        {
          "type": "text",
          "text": {
            "content": "2.1  Reversed Equation Judgment Task Curiosity  [s2_1_reversed_equation_judgment_task_curiosity]",
            "link": null
          },
          "annotations": {
            "bold": false,
            "italic": false,
            "strikethrough": false,
            "underline": false,
            "code": false,
            "color": "default"
          },
          "plain_text": "2.1  Reversed Equation Judgment Task Curiosity  [s2_1_reversed_equation_judgment_task_curiosity]",
          "href": null
        }
      ],
      "is_toggleable": false,
      "color": "default"
    },
    "archived": false
  },
  {
    "object": "block",
    "id": "3485917e-ac52-81ca-ba65-ea4cd963a311",
    "parent": {
      "type": "page_id",
      "page_id": "3485917e-ac52-8183-8657-cabc4a8e078c"
    },
    "created_time": "2026-04-20T17:01:00.000Z",
    "last_edited_time": "2026-04-20T17:01:00.000Z",
    "created_by": {
      "object": "user",
      "id": "31a5917e-ac52-8155-8199-00271e06ffde"
    },
    "last_edited_by": {
      "object": "user",
      "id": "31a5917e-ac52-8155-8199-00271e06ffde"
    },
    "has_children": false,
    "in_trash": false,
    "type": "callout",
    "callout": {
      "rich_text": [
        {
          "type": "text",
          "text": {
            "content": "Static equation appears: 5 × 2 = 10. Student's equation from previous section, now read-only.",
            "link": null
          },
          "annotations": {
            "bold": false,
            "italic": false,
            "strikethrough": false,
            "underline": false,
            "code": false,
            "color": "default"
          },
          "plain_text": "Static equation appears: 5 × 2 = 10. Student's equation from previous section, now read-only.",
          "href": null
        }
      ],
      "icon": {
        "type": "emoji",
        "emoji": "🎬"
      },
      "color": "default"
    },
    "archived": false
  },
  {
    "object": "block",
    "id": "3485917e-ac52-81d9-9896-d69fc7ecd5e2",
    "parent": {
      "type": "page_id",
      "page_id": "3485917e-ac52-8183-8657-cabc4a8e078c"
    },
    "created_time": "2026-04-20T17:01:00.000Z",
    "last_edited_time": "2026-04-20T17:01:00.000Z",
    "created_by": {
      "object": "user",
      "id": "31a5917e-ac52-8155-8199-00271e06ffde"
    },
    "last_edited_by": {
      "object": "user",
      "id": "31a5917e-ac52-8155-8199-00271e06ffde"
    },
    "has_children": false,
    "in_trash": false,
    "type": "callout",
    "callout": {
      "rich_text": [
        {
          "type": "text",
          "text": {
            "content": "Second equation appears alongside or below first: 10 = 5 × 2. Reversed orientation.",
            "link": null
          },
          "annotations": {
            "bold": false,
            "italic": false,
            "strikethrough": false,
            "underline": false,
            "code": false,
            "color": "default"
          },
          "plain_text": "Second equation appears alongside or below first: 10 = 5 × 2. Reversed orientation.",
          "href": null
        }
      ],
      "icon": {
        "type": "emoji",
        "emoji": "🎬"
      },
      "color": "default"
    },
    "archived": false
  },
  {
    "object": "block",
    "id": "3485917e-ac52-81f2-aabc-d8056592df2b",
    "parent": {
      "type": "page_id",
      "page_id": "3485917e-ac52-8183-8657-cabc4a8e078c"
    },
    "created_time": "2026-04-20T17:01:00.000Z",
    "last_edited_time": "2026-04-20T17:01:00.000Z",
    "created_by": {
      "object": "user",
      "id": "31a5917e-ac52-8155-8199-00271e06ffde"
    },
    "last_edited_by": {
      "object": "user",
      "id": "31a5917e-ac52-8155-8199-00271e06ffde"
    },
    "has_children": false,
    "in_trash": false,
    "type": "callout",
    "callout": {
      "rich_text": [
        {
          "type": "text",
          "text": {
            "content": "\"Now look at this equation. What do you think?\"",
            "link": null
          },
          "annotations": {
            "bold": false,
            "italic": false,
            "strikethrough": false,
            "underline": false,
            "code": false,
            "color": "default"
          },
          "plain_text": "\"Now look at this equation. What do you think?\"",
          "href": null
        }
      ],
      "icon": {
        "type": "emoji",
        "emoji": "💬"
      },
      "color": "default"
    },
    "archived": false
  },
  {
    "object": "block",
    "id": "3485917e-ac52-81a2-bb80-e7b54a8b0c5d",
    "parent": {
      "type": "page_id",
      "page_id": "3485917e-ac52-8183-8657-cabc4a8e078c"
    },
    "created_time": "2026-04-20T17:01:00.000Z",
    "last_edited_time": "2026-04-20T17:01:00.000Z",
    "created_by": {
      "object": "user",
      "id": "31a5917e-ac52-8155-8199-00271e06ffde"
    },
    "last_edited_by": {
      "object": "user",
      "id": "31a5917e-ac52-8155-8199-00271e06ffde"
    },
    "has_children": false,
    "in_trash": false,
    "type": "callout",
    "callout": {
      "rich_text": [
        {
          "type": "text",
          "text": {
            "content": "tool: multiple_choice  options: [\"It's true — both sides are 10\", \"It's true — it's just written differently\", \"It's wrong — the answer should come last\", \"I'm not sure\"]\n\"What do you think about 10 = 5 × 2?\"",
            "link": null
          },
          "annotations": {
            "bold": false,
            "italic": false,
            "strikethrough": false,
            "underline": false,
            "code": false,
            "color": "default"
          },
          "plain_text": "tool: multiple_choice  options: [\"It's true — both sides are 10\", \"It's true — it's just written differently\", \"It's wrong — the answer should come last\", \"I'm not sure\"]\n\"What do you think about 10 = 5 × 2?\"",
          "href": null
        }
      ],
      "icon": {
        "type": "emoji",
        "emoji": "❔"
      },
      "color": "default"
    },
    "archived": false
  },
  {
    "object": "block",
    "id": "3485917e-ac52-8106-b0cf-d91ceea7f4a0",
    "parent": {
      "type": "page_id",
      "page_id": "3485917e-ac52-8183-8657-cabc4a8e078c"
    },
    "created_time": "2026-04-20T17:01:00.000Z",
    "last_edited_time": "2026-04-20T17:01:00.000Z",
    "created_by": {
      "object": "user",
      "id": "31a5917e-ac52-8155-8199-00271e06ffde"
    },
    "last_edited_by": {
      "object": "user",
      "id": "31a5917e-ac52-8155-8199-00271e06ffde"
    },
    "has_children": true,
    "in_trash": false,
    "type": "toggle",
    "toggle": {
      "rich_text": [
        {
          "type": "text",
          "text": {
            "content": "✅ Student chose option A — checked both sides",
            "link": null
          },
          "annotations": {
            "bold": false,
            "italic": false,
            "strikethrough": false,
            "underline": false,
            "code": false,
            "color": "default"
          },
          "plain_text": "✅ Student chose option A — checked both sides",
          "href": null
        }
      ],
      "color": "default",
      "children": [
        {
          "object": "block",
          "id": "3485917e-ac52-81d8-aaef-e6fc66a03234",
          "parent": {
            "type": "block_id",
            "block_id": "3485917e-ac52-8106-b0cf-d91ceea7f4a0"
          },
          "created_time": "2026-04-20T17:01:00.000Z",
          "last_edited_time": "2026-04-20T17:01:00.000Z",
          "created_by": {
            "object": "user",
            "id": "31a5917e-ac52-8155-8199-00271e06ffde"
          },
          "last_edited_by": {
            "object": "user",
            "id": "31a5917e-ac52-8155-8199-00271e06ffde"
          },
          "has_children": false,
          "in_trash": false,
          "type": "callout",
          "callout": {
            "rich_text": [
              {
                "type": "text",
                "text": {
                  "content": "\"You checked both sides. Smart thinking. Hold that thought.\"",
                  "link": null
                },
                "annotations": {
                  "bold": false,
                  "italic": false,
                  "strikethrough": false,
                  "underline": false,
                  "code": false,
                  "color": "default"
                },
                "plain_text": "\"You checked both sides. Smart thinking. Hold that thought.\"",
                "href": null
              }
            ],
            "icon": {
              "type": "emoji",
              "emoji": "💬"
            },
            "color": "default"
          },
          "archived": false
        }
      ]
    },
    "archived": false
  },
  {
    "object": "block",
    "id": "3485917e-ac52-81e9-abbc-c836330d39ec",
    "parent": {
      "type": "page_id",
      "page_id": "3485917e-ac52-8183-8657-cabc4a8e078c"
    },
    "created_time": "2026-04-20T17:01:00.000Z",
    "last_edited_time": "2026-04-20T17:01:00.000Z",
    "created_by": {
      "object": "user",
      "id": "31a5917e-ac52-8155-8199-00271e06ffde"
    },
    "last_edited_by": {
      "object": "user",
      "id": "31a5917e-ac52-8155-8199-00271e06ffde"
    },
    "has_children": true,
    "in_trash": false,
    "type": "toggle",
    "toggle": {
      "rich_text": [
        {
          "type": "text",
          "text": {
            "content": "✅ Student chose option B — noticed it's the same equation flipped",
            "link": null
          },
          "annotations": {
            "bold": false,
            "italic": false,
            "strikethrough": false,
            "underline": false,
            "code": false,
            "color": "default"
          },
          "plain_text": "✅ Student chose option B — noticed it's the same equation flipped",
          "href": null
        }
      ],
      "color": "default",
      "children": [
        {
          "object": "block",
          "id": "3485917e-ac52-81f0-a7a0-db13fc82865a",
          "parent": {
            "type": "block_id",
            "block_id": "3485917e-ac52-81e9-abbc-c836330d39ec"
          },
          "created_time": "2026-04-20T17:01:00.000Z",
          "last_edited_time": "2026-04-20T17:01:00.000Z",
          "created_by": {
            "object": "user",
            "id": "31a5917e-ac52-8155-8199-00271e06ffde"
          },
          "last_edited_by": {
            "object": "user",
            "id": "31a5917e-ac52-8155-8199-00271e06ffde"
          },
          "has_children": false,
          "in_trash": false,
          "type": "callout",
          "callout": {
            "rich_text": [
              {
                "type": "text",
                "text": {
                  "content": "\"You noticed it's the same equation, just flipped. Hold that thought.\"",
                  "link": null
                },
                "annotations": {
                  "bold": false,
                  "italic": false,
                  "strikethrough": false,
                  "underline": false,
                  "code": false,
                  "color": "default"
                },
                "plain_text": "\"You noticed it's the same equation, just flipped. Hold that thought.\"",
                "href": null
              }
            ],
            "icon": {
              "type": "emoji",
              "emoji": "💬"
            },
            "color": "default"
          },
          "archived": false
        }
      ]
    },
    "archived": false
  },
  {
    "object": "block",
    "id": "3485917e-ac52-8114-ab0e-fd8da8a1a527",
    "parent": {
      "type": "page_id",
      "page_id": "3485917e-ac52-8183-8657-cabc4a8e078c"
    },
    "created_time": "2026-04-20T17:01:00.000Z",
    "last_edited_time": "2026-04-20T17:01:00.000Z",
    "created_by": {
      "object": "user",
      "id": "31a5917e-ac52-8155-8199-00271e06ffde"
    },
    "last_edited_by": {
      "object": "user",
      "id": "31a5917e-ac52-8155-8199-00271e06ffde"
    },
    "has_children": true,
    "in_trash": false,
    "type": "toggle",
    "toggle": {
      "rich_text": [
        {
          "type": "text",
          "text": {
            "content": "✅ Student chose option C — thinks answer must come last",
            "link": null
          },
          "annotations": {
            "bold": false,
            "italic": false,
            "strikethrough": false,
            "underline": false,
            "code": false,
            "color": "default"
          },
          "plain_text": "✅ Student chose option C — thinks answer must come last",
          "href": null
        }
      ],
      "color": "default",
      "children": [
        {
          "object": "block",
          "id": "3485917e-ac52-8108-a2c7-edfc41853a85",
          "parent": {
            "type": "block_id",
            "block_id": "3485917e-ac52-8114-ab0e-fd8da8a1a527"
          },
          "created_time": "2026-04-20T17:01:00.000Z",
          "last_edited_time": "2026-04-20T17:01:00.000Z",
          "created_by": {
            "object": "user",
            "id": "31a5917e-ac52-8155-8199-00271e06ffde"
          },
          "last_edited_by": {
            "object": "user",
            "id": "31a5917e-ac52-8155-8199-00271e06ffde"
          },
          "has_children": false,
          "in_trash": false,
          "type": "callout",
          "callout": {
            "rich_text": [
              {
                "type": "text",
                "text": {
                  "content": "\"Interesting. Something looks different about it. Hold that thought.\"",
                  "link": null
                },
                "annotations": {
                  "bold": false,
                  "italic": false,
                  "strikethrough": false,
                  "underline": false,
                  "code": false,
                  "color": "default"
                },
                "plain_text": "\"Interesting. Something looks different about it. Hold that thought.\"",
                "href": null
              }
            ],
            "icon": {
              "type": "emoji",
              "emoji": "💬"
            },
            "color": "default"
          },
          "archived": false
        }
      ]
    },
    "archived": false
  },
  {
    "object": "block",
    "id": "3485917e-ac52-8175-96da-fe4d9d54732d",
    "parent": {
      "type": "page_id",
      "page_id": "3485917e-ac52-8183-8657-cabc4a8e078c"
    },
    "created_time": "2026-04-20T17:01:00.000Z",
    "last_edited_time": "2026-04-20T17:01:00.000Z",
    "created_by": {
      "object": "user",
      "id": "31a5917e-ac52-8155-8199-00271e06ffde"
    },
    "last_edited_by": {
      "object": "user",
      "id": "31a5917e-ac52-8155-8199-00271e06ffde"
    },
    "has_children": true,
    "in_trash": false,
    "type": "toggle",
    "toggle": {
      "rich_text": [
        {
          "type": "text",
          "text": {
            "content": "✅ Student chose option D — uncertain",
            "link": null
          },
          "annotations": {
            "bold": false,
            "italic": false,
            "strikethrough": false,
            "underline": false,
            "code": false,
            "color": "default"
          },
          "plain_text": "✅ Student chose option D — uncertain",
          "href": null
        }
      ],
      "color": "default",
      "children": [
        {
          "object": "block",
          "id": "3485917e-ac52-811c-b689-fd2c968e0753",
          "parent": {
            "type": "block_id",
            "block_id": "3485917e-ac52-8175-96da-fe4d9d54732d"
          },
          "created_time": "2026-04-20T17:01:00.000Z",
          "last_edited_time": "2026-04-20T17:01:00.000Z",
          "created_by": {
            "object": "user",
            "id": "31a5917e-ac52-8155-8199-00271e06ffde"
          },
          "last_edited_by": {
            "object": "user",
            "id": "31a5917e-ac52-8155-8199-00271e06ffde"
          },
          "has_children": false,
          "in_trash": false,
          "type": "callout",
          "callout": {
            "rich_text": [
              {
                "type": "text",
                "text": {
                  "content": "\"That's honest. It does look different. Hold that thought.\"",
                  "link": null
                },
                "annotations": {
                  "bold": false,
                  "italic": false,
                  "strikethrough": false,
                  "underline": false,
                  "code": false,
                  "color": "default"
                },
                "plain_text": "\"That's honest. It does look different. Hold that thought.\"",
                "href": null
              }
            ],
            "icon": {
              "type": "emoji",
              "emoji": "💬"
            },
            "color": "default"
          },
          "archived": false
        }
      ]
    },
    "archived": false
  },
  {
    "object": "block",
    "id": "3485917e-ac52-815f-af12-d5d7b8df0532",
    "parent": {
      "type": "page_id",
      "page_id": "3485917e-ac52-8183-8657-cabc4a8e078c"
    },
    "created_time": "2026-04-20T17:01:00.000Z",
    "last_edited_time": "2026-04-20T17:01:00.000Z",
    "created_by": {
      "object": "user",
      "id": "31a5917e-ac52-8155-8199-00271e06ffde"
    },
    "last_edited_by": {
      "object": "user",
      "id": "31a5917e-ac52-8155-8199-00271e06ffde"
    },
    "has_children": false,
    "in_trash": false,
    "type": "paragraph",
    "paragraph": {
      "rich_text": [
        {
          "type": "text",
          "text": {
            "content": "⏭️ Student presses Next",
            "link": null
          },
          "annotations": {
            "bold": false,
            "italic": false,
            "strikethrough": false,
            "underline": false,
            "code": false,
            "color": "default"
          },
          "plain_text": "⏭️ Student presses Next",
          "href": null
        }
      ],
      "icon": null,
      "color": "default"
    },
    "archived": false
  },
  {
    "object": "block",
    "id": "3485917e-ac52-81f2-97e0-c150698ae419",
    "parent": {
      "type": "page_id",
      "page_id": "3485917e-ac52-8183-8657-cabc4a8e078c"
    },
    "created_time": "2026-04-20T17:01:00.000Z",
    "last_edited_time": "2026-04-20T17:01:00.000Z",
    "created_by": {
      "object": "user",
      "id": "31a5917e-ac52-8155-8199-00271e06ffde"
    },
    "last_edited_by": {
      "object": "user",
      "id": "31a5917e-ac52-8155-8199-00271e06ffde"
    },
    "has_children": false,
    "in_trash": false,
    "type": "callout",
    "callout": {
      "rich_text": [
        {
          "type": "text",
          "text": {
            "content": "\"You can build equations. But today, equations have some surprises. You'll see them in new ways and figure out missing numbers.\"",
            "link": null
          },
          "annotations": {
            "bold": false,
            "italic": false,
            "strikethrough": false,
            "underline": false,
            "code": false,
            "color": "default"
          },
          "plain_text": "\"You can build equations. But today, equations have some surprises. You'll see them in new ways and figure out missing numbers.\"",
          "href": null
        }
      ],
      "icon": {
        "type": "emoji",
        "emoji": "💬"
      },
      "color": "default"
    },
    "archived": false
  }
]
