{
  "id": "s2_1_transfer_circles",
  "incorrects": [
    [
      {
        "condition": {
          "selected": 2
        },
        "description": "Student selected 2, confusing items per container with container count",
        "is_correct": false,
        "steps": [
          [
            {
              "type": "scene",
              "method": "update",
              "tangible_id": "equal_groups_circles",
              "params": {
                "highlight_containers": true,
                "description": "All 4 circles highlight to show they are the groups."
              }
            },
            {
              "type": "dialogue",
              "text": "You counted what's inside. Count the circles themselves. Each circle is a group."
            }
          ]
        ]
      },
      {
        "condition": {
          "selected": 6
        },
        "description": "Student selected 6, possibly counting containers plus items",
        "is_correct": false,
        "steps": [
          [
            {
              "type": "scene",
              "method": "update",
              "tangible_id": "equal_groups_circles",
              "params": {
                "highlight_containers": true,
                "description": "All 4 circles highlight to show they are the groups."
              }
            },
            {
              "type": "dialogue",
              "text": "Don't count the dots yet. Just the circles. How many circles do you see?"
            }
          ]
        ]
      },
      {
        "condition": {
          "selected": 3
        },
        "description": "Student selected 3, miscounted containers",
        "is_correct": false,
        "steps": [
          [
            {
              "type": "scene",
              "method": "animate",
              "tangible_id": "equal_groups_circles",
              "params": {
                "event": "count_containers",
                "status": "confirmed",
                "description": "Circles highlight sequentially as they are counted: 1, 2, 3, 4."
              }
            },
            {
              "type": "dialogue",
              "text": "Let me show you. Count the circles with me: 1, 2, 3, 4. Four circles means four groups."
            }
          ]
        ]
      }
    ],
    [
      {
        "condition": {
          "selected": 1
        },
        "description": "Student selected 1, significant undercount",
        "is_correct": false,
        "steps": [
          [
            {
              "type": "scene",
              "method": "update",
              "tangible_id": "equal_groups_circles",
              "params": {
                "highlight_single_container": 0,
                "description": "First circle highlights to focus attention on counting its contents."
              }
            },
            {
              "type": "dialogue",
              "text": "Look at one circle. Count the dots inside. How many dots are in this one circle?"
            }
          ]
        ]
      },
      {
        "condition": {
          "selected": 3
        },
        "description": "Student selected 3, miscounted items in container",
        "is_correct": false,
        "steps": [
          [
            {
              "type": "scene",
              "method": "update",
              "tangible_id": "equal_groups_circles",
              "params": {
                "highlight_single_container": 0,
                "description": "First circle highlights to focus attention on counting its contents."
              }
            },
            {
              "type": "dialogue",
              "text": "Pick one circle and count carefully. Are there 2 dots or more?"
            }
          ]
        ]
      },
      {
        "condition": {
          "selected": 4
        },
        "description": "Student selected 4, confusing container count with items per container",
        "is_correct": false,
        "steps": [
          [
            {
              "type": "scene",
              "method": "animate",
              "tangible_id": "equal_groups_circles",
              "params": {
                "event": "zoom_container",
                "status": "confirmed",
                "description": "First circle zooms in. Dots inside are counted: 1, 2."
              }
            },
            {
              "type": "dialogue",
              "text": "You're counting the circles. Look inside ONE circle. Count just the dots in that circle: 1, 2. Two dots in each circle."
            }
          ]
        ]
      }
    ],
    [
      {
        "condition": {
          "selected": "2 groups of 4"
        },
        "description": "Student reversed groups and items per group",
        "is_correct": false,
        "steps": [
          [
            {
              "type": "scene",
              "method": "update",
              "tangible_id": "equal_groups_circles",
              "params": {
                "highlight_containers": true,
                "description": "All circles highlight to reinforce container count."
              }
            },
            {
              "type": "dialogue",
              "text": "You flipped them. How many circles? That's your groups. How many dots in one circle? That's in each group."
            }
          ]
        ]
      },
      {
        "condition": {
          "selected": "4 groups of 4"
        },
        "description": "Student counted groups correctly but stated wrong items per group",
        "is_correct": false,
        "steps": [
          [
            {
              "type": "scene",
              "method": "update",
              "tangible_id": "equal_groups_circles",
              "params": {
                "highlight_single_container": 0,
                "description": "First circle highlights. Dots inside pulse to draw attention."
              }
            },
            {
              "type": "dialogue",
              "text": "You have the groups right. Look inside one circle. Count the dots. Are there 4?"
            }
          ]
        ]
      },
      {
        "condition": {
          "selected": "2 groups of 2"
        },
        "description": "Student miscounted both groups and items per group",
        "is_correct": false,
        "steps": [
          [
            {
              "type": "scene",
              "method": "animate",
              "tangible_id": "equal_groups_circles",
              "params": {
                "event": "count_containers",
                "status": "confirmed",
                "description": "Circles highlight sequentially: 1, 2, 3, 4. Then first circle zooms. Dots counted: 1, 2."
              }
            },
            {
              "type": "dialogue",
              "text": "Let's count together. Circles: 1, 2, 3, 4. Four groups. Now one circle: 1, 2 dots. Two in each. So you have 4 groups of 2."
            }
          ]
        ]
      }
    ]
  ],
  "_generated_at": "2026-04-27T16:00:09.396904+00:00"
}