{
  "id": "s1_3_two_step_problem_identify_compare",
  "beats": [
    {
      "type": "scene",
      "method": "add",
      "tangible_id": "bar_graph_field_trip",
      "tangible_type": "bar_graph",
      "params": {
        "mode": "reading",
        "orientation": "vertical",
        "scale": 5,
        "axis_range": [
          0,
          60
        ],
        "categories": [
          "Aquarium",
          "Museum",
          "Zoo",
          "Park",
          "Farm"
        ],
        "values": [
          35,
          25,
          45,
          30,
          15
        ],
        "title": "Votes for Field Trip",
        "description": "Vertical bar graph appears. Votes for Field Trip. Five categories: Aquarium 35, Museum 25, Zoo 45, Park 30, Farm 15. Scale of 5, axis 0-60."
      }
    },
    {
      "type": "dialogue",
      "text": "How many fewer votes did the museum and farm combined get than the zoo?"
    },
    {
      "type": "prompt",
      "text": "What should we find first?",
      "tool": "multiple_choice",
      "options": [
        "Add museum and farm",
        "Compare zoo to museum",
        "Add all five places",
        "Subtract farm from museum"
      ],
      "validator": [
        {
          "condition_id": "correct",
          "condition": {
            "selected": "Add museum and farm"
          },
          "description": "Student selected Add museum and farm, correct first step",
          "is_correct": true,
          "beats": [
            {
              "type": "dialogue",
              "text": "Combine museum and farm first."
            }
          ]
        }
      ]
    },
    {
      "type": "current_scene",
      "elements": [
        {
          "tangible_id": "bar_graph_field_trip",
          "description": "Vertical bar graph. Votes for Field Trip. Five categories visible. Reading mode. Multiple choice tool active for first step.",
          "tangible_type": "bar_graph",
          "mode": "reading",
          "orientation": "vertical",
          "scale": 5,
          "axis_range": [
            0,
            60
          ],
          "categories": [
            "Aquarium",
            "Museum",
            "Zoo",
            "Park",
            "Farm"
          ]
        }
      ]
    },
    {
      "type": "scene",
      "method": "update",
      "tangible_id": "bar_graph_field_trip",
      "params": {
        "highlight_categories": [
          "Museum",
          "Farm"
        ],
        "description": "Museum bar (25) and Farm bar (15) highlight for step 2."
      }
    },
    {
      "type": "dialogue",
      "text": "What's the combined total of votes for the museum and farm?"
    },
    {
      "type": "prompt",
      "text": "How many votes did museum and farm get combined?",
      "tool": "multiple_choice",
      "options": [
        10,
        30,
        40,
        45
      ],
      "validator": [
        {
          "condition_id": "correct",
          "condition": {
            "selected": 40
          },
          "description": "Student selected 40, correct (25 + 15 = 40)",
          "is_correct": true,
          "beats": [
            {
              "type": "dialogue",
              "text": "40 combined."
            }
          ]
        }
      ]
    },
    {
      "type": "current_scene",
      "elements": [
        {
          "tangible_id": "bar_graph_field_trip",
          "description": "Vertical bar graph. Votes for Field Trip. Museum bar (25) and Farm bar (15) highlighted. Reading mode.",
          "tangible_type": "bar_graph",
          "mode": "reading",
          "orientation": "vertical",
          "scale": 5,
          "axis_range": [
            0,
            60
          ],
          "categories": [
            "Aquarium",
            "Museum",
            "Zoo",
            "Park",
            "Farm"
          ]
        }
      ]
    },
    {
      "type": "scene",
      "method": "update",
      "tangible_id": "bar_graph_field_trip",
      "params": {
        "highlight_categories": [
          "Zoo"
        ],
        "description": "Zoo bar (45) highlights for comparison step."
      }
    },
    {
      "type": "dialogue",
      "text": "Museum and farm combined is 40. Now find how many fewer votes they got than the zoo."
    },
    {
      "type": "prompt",
      "text": "How many fewer votes did the museum and farm combined get than the zoo?",
      "tool": "multiple_choice",
      "options": [
        85,
        45,
        40,
        5
      ],
      "validator": [
        {
          "condition_id": "correct",
          "condition": {
            "selected": 5
          },
          "description": "Student selected 5, correct (45 - 40 = 5)",
          "is_correct": true,
          "beats": [
            {
              "type": "dialogue",
              "text": "5 fewer. Museum and farm combined got 5 fewer votes than the zoo."
            }
          ]
        }
      ]
    },
    {
      "type": "current_scene",
      "elements": [
        {
          "tangible_id": "bar_graph_field_trip",
          "description": "Vertical bar graph. Votes for Field Trip. Zoo bar (45) highlighted. Reading mode.",
          "tangible_type": "bar_graph",
          "mode": "reading",
          "orientation": "vertical",
          "scale": 5,
          "axis_range": [
            0,
            60
          ],
          "categories": [
            "Aquarium",
            "Museum",
            "Zoo",
            "Park",
            "Farm"
          ]
        }
      ]
    }
  ],
  "_generated_at": "2026-04-27T15:54:20.038731+00:00"
}